imgbox/__init__.py
imgbox/_input.py
imgbox/_main.py
imgbox/_output.py
tests/conftest.py
tests/test_input.py
tests/test_main.py
tests/test_output.py
imgbox_cli-0.0.3.dist-info/LICENSE
imgbox_cli-0.0.3.dist-info/METADATA
imgbox_cli-0.0.3.dist-info/WHEEL
imgbox_cli-0.0.3.dist-info/entry_points.txt
imgbox_cli-0.0.3.dist-info/top_level.txt
imgbox_cli-0.0.3.dist-info/RECORD
