Metadata-Version: 2.1
Name: imgbox-cli
Version: 0.0.3
Summary: Command line interface for sharing images on imgbox.com
Author-email: plotski <plotski@example.org>
License: GPL-3.0-or-later
Project-URL: Repository, https://codeberg.org/plotski/imgbox-cli
Project-URL: Bug Tracker, https://codeberg.org/plotski/imgbox-cli/issues
Project-URL: Changelog, https://codeberg.org/plotski/imgbox-cli/raw/branch/master/NEWS
Classifier: Programming Language :: Python :: 3
Classifier: License :: OSI Approved :: GNU General Public License v3 or later (GPLv3+)
Classifier: Operating System :: OS Independent
Requires-Python: >=3.8
License-File: LICENSE
Requires-Dist: pyimgbox ==1.*
Provides-Extra: dev
Requires-Dist: pytest ; extra == 'dev'
Requires-Dist: pytest-asyncio ; extra == 'dev'
Requires-Dist: pytest-mock ; extra == 'dev'
Requires-Dist: pytest-httpserver ; extra == 'dev'
Requires-Dist: tox ; extra == 'dev'
Requires-Dist: coverage ; extra == 'dev'
Requires-Dist: pytest-cov ; extra == 'dev'
Requires-Dist: ruff ; extra == 'dev'
Requires-Dist: flake8 ; extra == 'dev'
Requires-Dist: isort ; extra == 'dev'
